var uncmuseum = {
"type": "FeatureCollection",
"crs": { "type": "name", "properties": { "name": "urn:ogc:def:crs:OGC:1.3:CRS84" } },
"features": [
{ "type": "Feature", "properties": { "id": 1, "descrip": "unc carolina basketball museum" }, "geometry": { "type": "Point", "coordinates": [ -79.0421549, 35.8999127 ] } }
]
}
